{
    "magicNumber" : 1385621965,
    "versionNumber" : 1,
    "levelName" : "Testmap",
    "objects" : [
        {
            "pos" : [ 0.0, -0.1, 0.0 ],
            "rot" : [ 0.0, 0.0, 0.0, 1.0 ],
            "scale" : [ 10.0, 1.0, 10.0 ],
            "modelType": "Floor"
        },
        {
            "pos" : [ -3.0, 0.0, 0.0 ],
            "rot" : [ 0.0, 0.0, 0.0, 1.0 ],
            "scale" : [ 1.0, 1.0, 1.0 ],
            "modelType" : "Wobbly"
        },
        {
            "pos" : [ 3.0, 0.0, 0.0 ],
            "rot" : [ 0.0, 0.0, 0.0, 1.0 ],
            "scale" : [ 1.0, 1.0, 1.0 ],
            "modelType" : "Wobbly"
        },
        {
            "pos" : [ 0.0, 0.0, -10.0 ],
            "rot" : [ 0.0, 0.0, 0.0, 1.0 ],
            "scale" : [ 1.0, 1.0, 1.0 ],
            "modelType" : "Character"
        },
        {
            "pos" : [ 0.0, 10.0, -10.0 ],
            "rot" : [ 0.0, 0.0, 0.0, 1.0 ],
            "scale" : [ 1.0, 1.0, 1.0 ],
            "modelType" : "Character"
        },
        {
            "pos" : [ -3.0, 0.0, -20.0 ],
            "rot" : [ 0.0, 0.0, 0.0, 1.0 ],
            "scale" : [ 1.0, 1.0, 1.0 ],
            "modelType" : "LowPolyChar"
        },
        {
            "pos" : [ 3.0, 0.0, -20.0 ],
            "rot" : [ 0.0, 0.0, 0.0, 1.0 ],
            "scale" : [ 1.0, 1.0, 1.0 ],
            "modelType" : "LowPolyChar"
        }
    ]
}
